rus2latin_date
