Metadata-Version: 1.1
Name: rus2latin-date
Version: 1.1
Summary: Utility for converting Russian date into Roman
Home-page: https://github.com/nevmenandr/rus2latin_date
Author: Boris Orekhov
Author-email: nevmenandr@gmail.com
License: GPL
Keywords: nlp dates russian latin calendar
Platform: UNKNOWN
Classifier: Natural Language :: Russian
Classifier: Programming Language :: Python :: 3.5
Classifier: Programming Language :: Python :: 3.6
Classifier: Topic :: Text Processing :: Linguistic
Classifier: Intended Audience :: Developers
